evals/__init__.py
evals/_version.py
evals/api.py
evals/bulk_runner.py
evals/client.py
evals/pipeline.py
evals/query_generator.py
evals/test_case.py
evals/test_utils.py
evals/utils.py
evals/metrics/__init__.py
evals/metrics/bertscore.py
evals/metrics/cohere_reranker_metric.py
evals/metrics/entailment_metric.py
evals/metrics/metric.py
evals/metrics/randomscore.py
deepevals-0.2.0.dist-info/METADATA
deepevals-0.2.0.dist-info/WHEEL
deepevals-0.2.0.dist-info/top_level.txt
deepevals-0.2.0.dist-info/RECORD
