Metadata-Version: 2.1
Name: deepevals
Version: 0.2.0
Summary: Eval
Home-page: https://github.com/mr-gpt/evals
Author: Twilix
Author-email: jacky@twilix.io
Requires-Dist: requests
Requires-Dist: tqdm
Requires-Dist: transformers
Requires-Dist: pytest
Requires-Dist: tabulate
